mangum_extra_handlers/__init__.py
mangum_extra_handlers/eventbridge_handler.py
mangum_extra_handlers/sns_handler.py
mangum_extra_handlers/sqs_handler.py
mangum_extra_handlers/websocket_handler.py
mangum_extra_handlers-0.1.1.dist-info/METADATA
mangum_extra_handlers-0.1.1.dist-info/WHEEL
mangum_extra_handlers-0.1.1.dist-info/top_level.txt
mangum_extra_handlers-0.1.1.dist-info/RECORD
